hep_tables/__init__.py
hep_tables/hep_table.py
hep_tables/local.py
hep_tables/np_functions.py
hep_tables/render.py
hep_tables/statements.py
hep_tables/utils.py
hep_tables-1.0.0.dist-info/LICENSE
hep_tables-1.0.0.dist-info/METADATA
hep_tables-1.0.0.dist-info/WHEEL
hep_tables-1.0.0.dist-info/top_level.txt
hep_tables-1.0.0.dist-info/RECORD
