Metadata-Version: 2.1
Name: hep-tables
Version: 1.0.0
Summary: Tables for structured data
Home-page: https://github.com/gordonwatts/hep_tables
Author: G. Watts (IRIS-HEP/UW Seattle)
Author-email: gwatts@uw.edu
Maintainer: Gordon Watts (IRIS-HEP/UW Seattle)
Maintainer-email: gwatts@uw.edu
License: TBD
Platform: Any
Classifier: Intended Audience :: Developers
Classifier: Intended Audience :: Information Technology
Classifier: Programming Language :: Python
Classifier: Programming Language :: Python :: 3.7
Classifier: Topic :: Software Development
Classifier: Topic :: Utilities
Requires-Python: >=3.6, <3.8
Requires-Dist: func-adl-xaod (<2a,>=1.1b1)
Requires-Dist: servicex (<3a,>=2b1)
Requires-Dist: dataframe-expressions (<2a,>=1b1)
Requires-Dist: make-it-sync
Provides-Extra: complete
Requires-Dist: asyncmock ; extra == 'complete'
Requires-Dist: coverage ; extra == 'complete'
Requires-Dist: flake8 ; extra == 'complete'
Requires-Dist: jupyter-book ; extra == 'complete'
Requires-Dist: jupyterlab ; extra == 'complete'
Requires-Dist: matplotlib ; extra == 'complete'
Requires-Dist: pytest ; extra == 'complete'
Requires-Dist: pytest-asyncio ; extra == 'complete'
Requires-Dist: pytest-cov ; extra == 'complete'
Requires-Dist: pytest-mock ; extra == 'complete'
Requires-Dist: twine ; extra == 'complete'
Requires-Dist: wheel ; extra == 'complete'
Provides-Extra: notebook
Requires-Dist: jupyterlab ; extra == 'notebook'
Requires-Dist: matplotlib ; extra == 'notebook'
Provides-Extra: test
Requires-Dist: pytest ; extra == 'test'
Requires-Dist: pytest-asyncio ; extra == 'test'
Requires-Dist: pytest-cov ; extra == 'test'
Requires-Dist: pytest-mock ; extra == 'test'
Requires-Dist: flake8 ; extra == 'test'
Requires-Dist: coverage ; extra == 'test'
Requires-Dist: twine ; extra == 'test'
Requires-Dist: wheel ; extra == 'test'
Requires-Dist: jupyter-book ; extra == 'test'
Requires-Dist: asyncmock ; extra == 'test'
